gzspidertools/__init__.py
gzspidertools/config.py
gzspidertools/exceptions.py
gzspidertools/extensions.py
gzspidertools/formatdata.py
gzspidertools/handlers.py
gzspidertools/items.py
gzspidertools/middlewares.py
gzspidertools/mongoclient.py
gzspidertools/mysqlclient.py
gzspidertools/pipelines.py
gzspidertools/request.py
gzspidertools/spiders.py
gzspidertools/commands/__init__.py
gzspidertools/commands/crawl.py
gzspidertools/commands/genspider.py
gzspidertools/commands/startproject.py
gzspidertools/commands/version.py
gzspidertools/common/__init__.py
gzspidertools/common/encryption.py
gzspidertools/common/expend.py
gzspidertools/common/mongodbpipe.py
gzspidertools/common/multiplexing.py
gzspidertools/common/mysqlerrhandle.py
gzspidertools/common/params.py
gzspidertools/common/postgreserrhandle.py
gzspidertools/common/spiderconf.py
gzspidertools/common/sqlformat.py
gzspidertools/common/typevars.py
gzspidertools/common/utils.py
gzspidertools/data/browsers.json
gzspidertools/extras/__init__.py
gzspidertools/extras/cvnpil.py
gzspidertools/extras/deduplicate.py
gzspidertools/extras/ext.py
gzspidertools/extras/oss.py
gzspidertools/scraper/__init__.py
gzspidertools/scraper/extensions/__init__.py
gzspidertools/scraper/extensions/prometheus/PrometheusWebService.py
gzspidertools/scraper/extensions/prometheus/__init__.py
gzspidertools/scraper/handlers/__init__.py
gzspidertools/scraper/handlers/aiohttp/AiohttpDownloadHandler.py
gzspidertools/scraper/handlers/aiohttp/__init__.py
gzspidertools/scraper/handlers/aiohttp/parser.py
gzspidertools/scraper/handlers/impersonate/ImpersonateDownloadHandler.py
gzspidertools/scraper/handlers/impersonate/__init__.py
gzspidertools/scraper/handlers/impersonate/parser.py
gzspidertools/scraper/http/__init__.py
gzspidertools/scraper/http/request/__init__.py
gzspidertools/scraper/http/request/aiohttp.py
gzspidertools/scraper/middlewares/__init__.py
gzspidertools/scraper/middlewares/drissionpage/__init__.py
gzspidertools-0.0.30.dist-info/METADATA
gzspidertools-0.0.30.dist-info/WHEEL
gzspidertools-0.0.30.dist-info/entry_points.txt
gzspidertools-0.0.30.dist-info/licenses/LICENSE
gzspidertools-0.0.30.dist-info/RECORD
